wx/__init__.py
wx/adv.py
wx/aui.py
wx/dataview.py
wx/grid.py
wx/html.py
wx/html2.py
wx/media.py
wx/propgrid.py
wx/ribbon.py
wx/richtext.py
wx/stc.py
wx/xml.py
wx/xrc.py
wx/lib/CDate.py
wx/lib/ClickableHtmlWindow.py
wx/lib/__init__.py
wx/lib/activex.py
wx/lib/activexwrapper.py
wx/lib/anchors.py
wx/lib/busy.py
wx/lib/buttons.py
wx/lib/calendar.py
wx/lib/colourdb.py
wx/lib/colourselect.py
wx/lib/colourutils.py
wx/lib/combotreebox.py
wx/lib/delayedresult.py
wx/lib/dialogs.py
wx/lib/docview.py
wx/lib/dragscroller.py
wx/lib/embeddedimage.py
wx/lib/eventStack.py
wx/lib/eventwatcher.py
wx/lib/evtmgr.py
wx/lib/expando.py
wx/lib/fancytext.py
wx/lib/filebrowsebutton.py
wx/lib/flashwin.py
wx/lib/flashwin_old.py
wx/lib/foldmenu.py
wx/lib/gestures.py
wx/lib/graphics.py
wx/lib/gridmovers.py
wx/lib/iewin.py
wx/lib/iewin_old.py
wx/lib/imagebrowser.py
wx/lib/imageutils.py
wx/lib/infoframe.py
wx/lib/inspection.py
wx/lib/intctrl.py
wx/lib/itemspicker.py
wx/lib/langlistctrl.py
wx/lib/layoutf.py
wx/lib/msgpanel.py
wx/lib/multisash.py
wx/lib/newevent.py
wx/lib/nvdlg.py
wx/lib/pdfwin.py
wx/lib/pdfwin_old.py
wx/lib/platebtn.py
wx/lib/popupctl.py
wx/lib/printout.py
wx/lib/progressindicator.py
wx/lib/pydocview.py
wx/lib/rcsizer.py
wx/lib/resizewidget.py
wx/lib/scrolledpanel.py
wx/lib/sheet.py
wx/lib/sized_controls.py
wx/lib/softwareupdate.py
wx/lib/splitter.py
wx/lib/statbmp.py
wx/lib/stattext.py
wx/lib/throbber.py
wx/lib/ticker.py
wx/lib/ticker_xrc.py
wx/lib/utils.py
wx/lib/wordwrap.py
wx/lib/wxpTag.py
wx/lib/agw/__init__.py
wx/lib/agw/advancedsplash.py
wx/lib/agw/aquabutton.py
wx/lib/agw/artmanager.py
wx/lib/agw/balloontip.py
wx/lib/agw/buttonpanel.py
wx/lib/agw/cubecolourdialog.py
wx/lib/agw/customtreectrl.py
wx/lib/agw/flatmenu.py
wx/lib/agw/flatnotebook.py
wx/lib/agw/floatspin.py
wx/lib/agw/fmcustomizedlg.py
wx/lib/agw/fmresources.py
wx/lib/agw/foldpanelbar.py
wx/lib/agw/fourwaysplitter.py
wx/lib/agw/genericmessagedialog.py
wx/lib/agw/gradientbutton.py
wx/lib/agw/hyperlink.py
dummy_wx-0.3.0.dist-info/LICENSE
dummy_wx-0.3.0.dist-info/METADATA
dummy_wx-0.3.0.dist-info/WHEEL
dummy_wx-0.3.0.dist-info/top_level.txt
dummy_wx-0.3.0.dist-info/RECORD
