Metadata-Version: 2.1
Name: dummy-wx
Version: 0.3.0
Summary: This module does nothing.
Home-page: https://github.com/domdfcoding/dummy_wx
Author: Dominic Davis-Foster
Author-email: dominic@davis-foster.co.uk
License: GNU Lesser General Public License v3 or later (LGPLv3+)
Project-URL: Issue_Tracker, https://github.com/domdfcoding/dummy_wx/issues
Project-URL: Source_Code, https://github.com/domdfcoding/dummy_wx
Keywords: wxpython,sphinx
Platform: Windows
Platform: macOS
Platform: Linux
Classifier: Intended Audience :: Developers
Classifier: License :: OSI Approved :: GNU Lesser General Public License v3 or later (LGPLv3+)
Classifier: Operating System :: OS Independent
Classifier: Programming Language :: Python
Classifier: Programming Language :: Python :: 3 :: Only
Classifier: Programming Language :: Python :: 3.6
Classifier: Programming Language :: Python :: 3.7
Classifier: Programming Language :: Python :: 3.8
Classifier: Programming Language :: Python :: Implementation :: CPython
Classifier: Topic :: Utilities
Requires-Python: >=3.6.1
Provides-Extra: all
